{
  "alias": "moonriver",
  "decimals": 18,
  "explorer": {
    "browserUrl": "https://moonriver.moonscan.io/",
    "provider": "etherscan"
  },
  "id": "1285",
  "name": "Moonriver",
  "providers": [
    {
      "alias": "default",
      "rpcUrl": "https://rpc.api.moonriver.moonbeam.network"
    },
    {
      "alias": "publicnode",
      "rpcUrl": "https://moonriver-rpc.publicnode.com"
    },
    {
      "alias": "drpc",
      "homepageUrl": "https://drpc.org/"
    }
  ],
  "symbol": "MOVR",
  "testnet": false
}
