{
  "alias": "unichain",
  "decimals": 18,
  "explorer": {
    "browserUrl": "https://uniscan.xyz/",
    "provider": "etherscan"
  },
  "id": "130",
  "name": "Unichain",
  "providers": [
    {
      "alias": "default",
      "rpcUrl": "https://mainnet.unichain.org/"
    },
    {
      "alias": "publicnode",
      "rpcUrl": "https://unichain-rpc.publicnode.com"
    },
    {
      "alias": "alchemy",
      "homepageUrl": "https://alchemy.com"
    },
    {
      "alias": "drpc",
      "homepageUrl": "https://drpc.org"
    },
    {
      "alias": "quicknode",
      "homepageUrl": "https://quicknode.com"
    }
  ],
  "symbol": "ETH",
  "testnet": false
}
